material/__init__.py
material/plugins/__init__.py
material/plugins/search/__init__.py
material/plugins/search/plugin.py
material/plugins/tags/__init__.py
material/plugins/tags/plugin.py
mkdocs_brudi-0.9.1.dist-info/LICENSE
mkdocs_brudi-0.9.1.dist-info/METADATA
mkdocs_brudi-0.9.1.dist-info/WHEEL
mkdocs_brudi-0.9.1.dist-info/entry_points.txt
mkdocs_brudi-0.9.1.dist-info/top_level.txt
mkdocs_brudi-0.9.1.dist-info/RECORD
