Metadata-Version: 2.1
Name: mkdocs-brudi
Version: 0.9.1
Summary: A brudi theme for MkDocs based on mkdocs-brudi
Home-page: https://squidfunk.github.io/mkdocs-material/
Author: brudi
Author-email: admin@brudi.io
License: MIT
Project-URL: Source, https://github.com/brudi/mkdocs-brudi
Keywords: mkdocs,documentation,theme
Platform: UNKNOWN
Classifier: Development Status :: 5 - Production/Stable
Classifier: Environment :: Web Environment
Classifier: License :: OSI Approved :: MIT License
Classifier: Programming Language :: JavaScript
Classifier: Programming Language :: Python
Classifier: Topic :: Documentation
Classifier: Topic :: Software Development :: Documentation
Classifier: Topic :: Text Processing :: Markup :: HTML
Requires-Python: >=3.6
License-File: LICENSE
Requires-Dist: jinja2 (>=2.11.1)
Requires-Dist: markdown (>=3.2)
Requires-Dist: mkdocs (>=1.3.0)
Requires-Dist: mkdocs-material-extensions (>=1.0.3)
Requires-Dist: pygments (>=2.10)
Requires-Dist: pymdown-extensions (>=9.0)
